django_amis_render/__init__.py
django_amis_render/admin.py
django_amis_render/amis_update.py
django_amis_render/apps.py
django_amis_render/auto_add.py
django_amis_render/auto_add_app.py
django_amis_render/customrenderer_amis.py
django_amis_render/default_list.py
django_amis_render/get_app_url_base.py
django_amis_render/get_url_from_name.py
django_amis_render/jhtml_render.py
django_amis_render/models.py
django_amis_render/my_custom_view.py
django_amis_render/tests.py
django_amis_render/urls.py
django_amis_render/urls_template.py
django_amis_render/views.py
django_amis_render/migrations/0001_initial.py
django_amis_render/migrations/0002_auto_20211115_1543.py
django_amis_render/migrations/0003_remove_amisrenderlist_temp_json_url_name.py
django_amis_render/migrations/0004_amisrenderapp.py
django_amis_render/migrations/0005_auto_20211122_1201.py
django_amis_render/migrations/0006_alter_amisrenderlist_json_file_url.py
django_amis_render/migrations/__init__.py
django_amis_render/static/amis-editor-demo/editor.html
django_amis_render/static/amis-editor-demo/index.html
django_amis_render/static/amis-editor-demo/schema.json
django_amis_render/static/amis-editor-demo/n/@fortawesome/fontawesome-free/webfonts/fa-brands-400_1a575a4.woff
django_amis_render/static/amis-editor-demo/n/@fortawesome/fontawesome-free/webfonts/fa-brands-400_1d5619c.svg
django_amis_render/static/amis-editor-demo/n/@fortawesome/fontawesome-free/webfonts/fa-brands-400_513aa60.ttf
django_amis_render/static/amis-editor-demo/n/@fortawesome/fontawesome-free/webfonts/fa-brands-400_592643a.eot
django_amis_render/static/amis-editor-demo/n/@fortawesome/fontawesome-free/webfonts/fa-brands-400_ed311c7.woff2
django_amis_render/static/amis-editor-demo/n/@fortawesome/fontawesome-free/webfonts/fa-regular-400_766913e.ttf
django_amis_render/static/amis-editor-demo/n/@fortawesome/fontawesome-free/webfonts/fa-regular-400_b0e2db3.eot
django_amis_render-0.0.8.dist-info/LICENSE
django_amis_render-0.0.8.dist-info/METADATA
django_amis_render-0.0.8.dist-info/WHEEL
django_amis_render-0.0.8.dist-info/top_level.txt
django_amis_render-0.0.8.dist-info/RECORD
