Metadata-Version: 2.1
Name: django-amis-render
Version: 0.0.8
Summary: a django app to render amis json file to web.
Home-page: https://github.com/Jiangshan00001/django_amis_render
Author: jiangshan00000
Author-email: 710806594@qq.com
License: UNKNOWN
Platform: UNKNOWN
Classifier: Programming Language :: Python :: 3
Classifier: License :: OSI Approved :: MIT License
Classifier: Operating System :: OS Independent
Requires-Dist: django
